{
  "$schema": "../gen/schemas/desktop-schema.json",
  "identifier": "default",
  "description": "Capability for the main window",
  "windows": ["main"],
  "permissions": [
    "core:default",
    "opener:default",
    "shell:default",
    "shell:allow-stdin-write",
    {
      "identifier": "shell:allow-execute",
      "allow": [
        {
          "name": "python-worker",
          "sidecar": true
        }
      ]
    },
    {
      "identifier": "shell:allow-spawn",
      "allow": [
        {
          "name": "python-worker",
          "sidecar": true
        }
      ]
    }
  ]
}
